fypy-1.0.1-py3.10-nspkg.pth
fypy/version.py
fypy/ahi/__init__.py
fypy/ahi/ahi_read_hsd.py
fypy/ahi/ahiconfig.py
fypy/ahi/ahiscene.py
fypy/ahi/ahisearchtable.py
fypy/ahi/geometry.py
fypy/anusplin/__init__.py
fypy/anusplin/anusplin.py
fypy/arcpy/Feature.py
fypy/arcpy/Raster.py
fypy/arcpy/__init__.py
fypy/arcpy/ConvertionTools/ToRaster.py
fypy/arcpy/ConvertionTools/__init__.py
fypy/calc/basic.py
fypy/fy3/__init__.py
fypy/fy3/fy3config.py
fypy/fy3/fy3core.py
fypy/fy3/fy3scene.py
fypy/fy4/__init__.py
fypy/fy4/fy4config.py
fypy/fy4/fy4core.py
fypy/fy4/fy4scene.py
fypy/gf/__init__.py
fypy/gf/gfscene.py
fypy/landsat/__init__.py
fypy/landsat/landsatscene.py
fypy/modis/__init__.py
fypy/modis/modisconfig.py
fypy/modis/modiscore.py
fypy/modis/modisscene.py
fypy/sentinel/__init__.py
fypy/sentinel/sentinelscene.py
fypy/tools/BaseAlgorithms.py
fypy/tools/RasterAndVector.py
fypy/tools/__init__.py
fypy/tools/gifpro.py
fypy/tools/h4toh5.py
fypy/tools/hdf4pro.py
fypy/tools/hdfpro.py
fypy/tools/interpolate.py
fypy/tools/jsonpro.py
fypy/tools/nc2tif.py
fypy/tools/ncpro.py
fypy/tools/readStationFile.py
fypy/tools/tifpro.py
fypy/tools/warp.py
fypy-1.0.1.dist-info/LICENSE
fypy-1.0.1.dist-info/METADATA
fypy-1.0.1.dist-info/WHEEL
fypy-1.0.1.dist-info/namespace_packages.txt
fypy-1.0.1.dist-info/top_level.txt
fypy-1.0.1.dist-info/RECORD
