Metadata-Version: 2.1
Name: fypy
Version: 1.0.1
Summary: fypy Package for FENGYUN Satellite 
Home-page: https://github.com/libin033/fypy
Author: The fypy Team
License: MIT
Keywords: FengYun,Meteorology,RemoteSensing
Platform: windows
Platform: linux
Classifier: Development Status :: 3 - Alpha
Classifier: Intended Audience :: Developers
Classifier: Topic :: Software Development :: Build Tools
Classifier: License :: OSI Approved :: MIT License
Classifier: Programming Language :: Python :: 3
Requires-Python: >=3.7
License-File: LICENSE
Requires-Dist: numpy >=1.2.0
Requires-Dist: h5py >=1.0.0
Requires-Dist: netcdf4 >=1.0.0
Requires-Dist: tqdm >=4.0.0
Requires-Dist: gdal >=2.0.0
Requires-Dist: pyshp >=2.1.0
Requires-Dist: imageio >=2.15.0
